wialon/__init__.py
wialon/exceptions.py
wialon/py.typed
wialon/sdk.py
wialon-1.1.5.dist-info/licenses/LICENSE
wialon-1.1.5.dist-info/METADATA
wialon-1.1.5.dist-info/WHEEL
wialon-1.1.5.dist-info/top_level.txt
wialon-1.1.5.dist-info/RECORD
