Metadata-Version: 2.4
Name: wialon
Version: 1.1.5
Summary: Wialon Remote API SDK for Python
Author-email: "Golden M, Inc." <software@goldenm.com>
Maintainer-email: Kenny Mochizuki <kenny@goldenm.com>
License-Expression: MIT
Project-URL: Repository, https://github.com/goldenm-software/wialon-python
Project-URL: Changelog, https://github.com/goldenm-software/wialon-python/blob/main/CHANGELOG.md
Keywords: wialon,wialon-sdk,wialon-api,wialon-python,gps-tracking,fleet-management,vehicle-tracking,gps-api,remote-api,layrz,goldenm
Classifier: Programming Language :: Python :: 3
Classifier: Programming Language :: Python :: 3.8
Classifier: Programming Language :: Python :: 3.9
Classifier: Programming Language :: Python :: 3.10
Classifier: Programming Language :: Python :: 3.11
Classifier: Programming Language :: Python :: 3.12
Classifier: Programming Language :: Python :: 3.13
Classifier: Programming Language :: Python :: 3.14
Classifier: Development Status :: 5 - Production/Stable
Classifier: Operating System :: OS Independent
Requires-Python: >=3.8
License-File: LICENSE
Requires-Dist: requests>=2.32.4
Dynamic: license-file
